{
  "saved_at": "2026-06-28T18:41:45.576Z",
  "items": [
    {
      "creator": "Protection Cluster",
      "title": "Yemen: Sa'ada Hub Reach (Jan-Mar)",
      "link": "https://reliefweb.int/report/yemen/saada-hub-reach-jan-mar",
      "pubDate": "Sun, 28 Jun 2026 11:40:33 +0000",
      "author": "Protection Cluster",
      "enclosure": {
        "url": "https://reliefweb.int/attachments/17b66207-2a91-4e80-baa8-9e2a10d18662/Sa%27ada%20Hub%20Reach%20%28Jan-Mar%29.pdf",
        "length": "2808661",
        "type": "application/pdf"
      },
      "content": "\n                            <div class=\"tag country\">Country: Yemen</div>\n                                      <div class=\"tag source\">Source: Protection Cluster</div>\n                                          <p><img src=\"https://reliefweb.int/sites/default/files/styles/thumbnail/public/previews/17/b6/17b66207-2a91-4e80-baa8-9e2a10d18662.png\" alt></p>\n                        <p>Please refer to the attached file.</p>\n                      \n      \n      ",
      "contentSnippet": "Country: Yemen\nSource: Protection Cluster\n\nPlease refer to the attached file.",
      "guid": "https://reliefweb.int/report/yemen/saada-hub-reach-jan-mar",
      "categories": [
        "Yemen",
        "Protection Cluster"
      ],
      "isoDate": "2026-06-28T11:40:33.000Z"
    },
    {
      "creator": "Protection Cluster",
      "title": "Yemen: Ibb Hub Reach (Jan-Mar)",
      "link": "https://reliefweb.int/report/yemen/ibb-hub-reach-jan-mar",
      "pubDate": "Sun, 28 Jun 2026 11:37:03 +0000",
      "author": "Protection Cluster",
      "enclosure": {
        "url": "https://reliefweb.int/attachments/118aa37f-0e02-4f82-804d-0017dcd14540/Ibb%20Hub%20Reach%20%28Jan-Mar%29.pdf",
        "length": "2837269",
        "type": "application/pdf"
      },
      "content": "\n                            <div class=\"tag country\">Country: Yemen</div>\n                                      <div class=\"tag source\">Source: Protection Cluster</div>\n                                          <p><img src=\"https://reliefweb.int/sites/default/files/styles/thumbnail/public/previews/11/8a/118aa37f-0e02-4f82-804d-0017dcd14540.png\" alt></p>\n                        <p>Please refer to the attached file.</p>\n                      \n      \n      ",
      "contentSnippet": "Country: Yemen\nSource: Protection Cluster\n\nPlease refer to the attached file.",
      "guid": "https://reliefweb.int/report/yemen/ibb-hub-reach-jan-mar",
      "categories": [
        "Yemen",
        "Protection Cluster"
      ],
      "isoDate": "2026-06-28T11:37:03.000Z"
    },
    {
      "creator": "Protection Cluster",
      "title": "Yemen: Al Hudaydah Hub Reach (Jan-Mar)",
      "link": "https://reliefweb.int/report/yemen/al-hudaydah-hub-reach-jan-mar",
      "pubDate": "Sun, 28 Jun 2026 11:35:50 +0000",
      "author": "Protection Cluster",
      "enclosure": {
        "url": "https://reliefweb.int/attachments/f0e31546-c176-418e-bfdf-7aadc332e94c/Al%20Hudaydah%20Hub%20Reach%20%28Jan-Mar%29.pdf",
        "length": "2872766",
        "type": "application/pdf"
      },
      "content": "\n                            <div class=\"tag country\">Country: Yemen</div>\n                                      <div class=\"tag source\">Source: Protection Cluster</div>\n                                          <p><img src=\"https://reliefweb.int/sites/default/files/styles/thumbnail/public/previews/f0/e3/f0e31546-c176-418e-bfdf-7aadc332e94c.png\" alt></p>\n                        <p>Please refer to the attached file.</p>\n                      \n      \n      ",
      "contentSnippet": "Country: Yemen\nSource: Protection Cluster\n\nPlease refer to the attached file.",
      "guid": "https://reliefweb.int/report/yemen/al-hudaydah-hub-reach-jan-mar",
      "categories": [
        "Yemen",
        "Protection Cluster"
      ],
      "isoDate": "2026-06-28T11:35:50.000Z"
    },
    {
      "creator": "Protection Cluster",
      "title": "Yemen: Sana'a Hub Reach (Jan-Mar)",
      "link": "https://reliefweb.int/report/yemen/sanaa-hub-reach-jan-mar",
      "pubDate": "Sun, 28 Jun 2026 11:31:19 +0000",
      "author": "Protection Cluster",
      "enclosure": {
        "url": "https://reliefweb.int/attachments/07996236-9fa5-4d73-9e92-7bde46cf2a13/Sana%27a%20Hub%20Reach%20%28Jan-Mar%29.pdf",
        "length": "2924200",
        "type": "application/pdf"
      },
      "content": "\n                            <div class=\"tag country\">Country: Yemen</div>\n                                      <div class=\"tag source\">Source: Protection Cluster</div>\n                                          <p><img src=\"https://reliefweb.int/sites/default/files/styles/thumbnail/public/previews/07/99/07996236-9fa5-4d73-9e92-7bde46cf2a13.png\" alt></p>\n                        <p>Please refer to the attached file.</p>\n                      \n      \n      ",
      "contentSnippet": "Country: Yemen\nSource: Protection Cluster\n\nPlease refer to the attached file.",
      "guid": "https://reliefweb.int/report/yemen/sanaa-hub-reach-jan-mar",
      "categories": [
        "Yemen",
        "Protection Cluster"
      ],
      "isoDate": "2026-06-28T11:31:19.000Z"
    },
    {
      "creator": "UN Office for the Coordination of Humanitarian Affairs",
      "title": "South Sudan Humanitarian Update as of 26 June 2026",
      "link": "https://reliefweb.int/report/south-sudan/south-sudan-humanitarian-update-26-june-2026",
      "pubDate": "Sun, 28 Jun 2026 11:21:05 +0000",
      "author": "UN Office for the Coordination of Humanitarian Affairs",
      "enclosure": {
        "url": "https://reliefweb.int/attachments/a9ba0a18-1935-41e5-94cb-187d41946e35/20260627%20South%20Sudan%20Humanitarian%20Update.pdf",
        "length": "2959884",
        "type": "application/pdf"
      },
      "content": "\n                            <div class=\"tag country\">Country: South Sudan</div>\n                                      <div class=\"tag source\">Source: UN Office for the Coordination of Humanitarian Affairs</div>\n                                                                                                <p><img src=\"https://reliefweb.int/sites/default/files/styles/thumbnail/public/previews/a9/ba/a9ba0a18-1935-41e5-94cb-187d41946e35.png\" alt></p>\n                        <p>Please refer to the attached file.</p>\n                        <ol><li><strong>Latest seasonal forecasts indicate a high likelihood of below-average rainfall and above-average temperatures across much of South Sudan during the June–September rainy season.</strong></li>\n<li><strong>A substantial number of IDPs have reportedly returned to Akobo, Jonglei State, following an improvement in the security situation.</strong></li>\n<li><strong>An estimated 22,000 people in Udier Payam, Longochuk County, Upper Nile State, are in urgent need of humanitarian assistance, according to a recently concluded Inter-Agency Rapid Needs Assessment.</strong></li>\n<li><strong>The Emergency Relief Coordinator, Tom Fletcher, has announced an allocation of US$6 million for Ebola operational readiness in South Sudan.</strong></li>\n</ol>\n              \n      \n      ",
      "contentSnippet": "Country: South Sudan\nSource: UN Office for the Coordination of Humanitarian Affairs\n\nPlease refer to the attached file.\nLatest seasonal forecasts indicate a high likelihood of below-average rainfall and above-average temperatures across much of South Sudan during the June–September rainy season.\nA substantial number of IDPs have reportedly returned to Akobo, Jonglei State, following an improvement in the security situation.\nAn estimated 22,000 people in Udier Payam, Longochuk County, Upper Nile State, are in urgent need of humanitarian assistance, according to a recently concluded Inter-Agency Rapid Needs Assessment.\nThe Emergency Relief Coordinator, Tom Fletcher, has announced an allocation of US$6 million for Ebola operational readiness in South Sudan.",
      "guid": "https://reliefweb.int/report/south-sudan/south-sudan-humanitarian-update-26-june-2026",
      "categories": [
        "South Sudan",
        "UN Office for the Coordination of Humanitarian Affairs",
        "Coordination",
        "Food and Nutrition",
        "Health",
        "Humanitarian Financing",
        "Protection and Human Rights",
        "Shelter and Non-Food Items",
        "Water Sanitation Hygiene",
        "Situation Report",
        "Epidemic",
        "Flood"
      ],
      "isoDate": "2026-06-28T11:21:05.000Z"
    },
    {
      "creator": "Protection Cluster",
      "title": "Yemen: Aden Hub Reach (Jan-Mar)",
      "link": "https://reliefweb.int/report/yemen/aden-hub-reach-jan-mar",
      "pubDate": "Sun, 28 Jun 2026 11:17:51 +0000",
      "author": "Protection Cluster",
      "enclosure": {
        "url": "https://reliefweb.int/attachments/7441d22c-c390-4b8b-8b89-7bbbbc74951d/Aden%20Hub%20Reach%20%28Jan-Mar%29.pdf",
        "length": "3115009",
        "type": "application/pdf"
      },
      "content": "\n                            <div class=\"tag country\">Country: Yemen</div>\n                                      <div class=\"tag source\">Source: Protection Cluster</div>\n                                          <p><img src=\"https://reliefweb.int/sites/default/files/styles/thumbnail/public/previews/74/41/7441d22c-c390-4b8b-8b89-7bbbbc74951d.png\" alt></p>\n                        <p>Please refer to the attached file.</p>\n                      \n      \n      ",
      "contentSnippet": "Country: Yemen\nSource: Protection Cluster\n\nPlease refer to the attached file.",
      "guid": "https://reliefweb.int/report/yemen/aden-hub-reach-jan-mar",
      "categories": [
        "Yemen",
        "Protection Cluster"
      ],
      "isoDate": "2026-06-28T11:17:51.000Z"
    },
    {
      "creator": "United Nations Population Fund",
      "title": "Afghanistan: ADIWG WG MEETING 24 June, 2026",
      "link": "https://reliefweb.int/report/afghanistan/adiwg-wg-meeting-24-june-2026",
      "pubDate": "Sun, 28 Jun 2026 09:37:58 +0000",
      "author": "United Nations Population Fund",
      "enclosure": {
        "url": "https://reliefweb.int/attachments/da009dc6-4c4e-462d-9cf4-8047d3477335/ADIWG%20WG%20MEETING%2024%20June%2C%202026.pdf",
        "length": "5941721",
        "type": "application/pdf"
      },
      "content": "\n                            <div class=\"tag country\">Country: Afghanistan</div>\n                                      <div class=\"tag source\">Source: United Nations Population Fund</div>\n                                          <p><img src=\"https://reliefweb.int/sites/default/files/styles/thumbnail/public/previews/da/00/da009dc6-4c4e-462d-9cf4-8047d3477335.png\" alt></p>\n                        <p>Please refer to the attached file.</p>\n                      \n      \n      ",
      "contentSnippet": "Country: Afghanistan\nSource: United Nations Population Fund\n\nPlease refer to the attached file.",
      "guid": "https://reliefweb.int/report/afghanistan/adiwg-wg-meeting-24-june-2026",
      "categories": [
        "Afghanistan",
        "United Nations Population Fund"
      ],
      "isoDate": "2026-06-28T09:37:58.000Z"
    },
    {
      "creator": "World Food Programme",
      "title": "WFP Somalia Country Brief June 2026",
      "link": "https://reliefweb.int/report/somalia/wfp-somalia-country-brief-june-2026",
      "pubDate": "Sun, 28 Jun 2026 07:56:56 +0000",
      "author": "World Food Programme",
      "enclosure": {
        "url": "https://reliefweb.int/attachments/9a1074af-073a-4051-aaed-81aac884532d/WFP%20Somalia%20Country%20Brief%20June%202026.pdf",
        "length": "386180",
        "type": "application/pdf"
      },
      "content": "\n                            <div class=\"tag country\">Country: Somalia</div>\n                                      <div class=\"tag source\">Source: World Food Programme</div>\n                                          <p><img src=\"https://reliefweb.int/sites/default/files/styles/thumbnail/public/previews/9a/10/9a1074af-073a-4051-aaed-81aac884532d.png\" alt></p>\n                        <p>Please refer to the attached file.</p>\n                        <ul><li>Somalia’s food security and nutrition situation is worsening beyond earlier projections, driven by consecutive failed rains, reduced humanitarian funding, and spillover effects from the Middle East crisis. Around <a rel=\"noreferrer noopener\" target=\"_blank\" href=\"https://fsnau.org/downloads/IPC_Somalia_Projection_Update_Acute_Food_Insecurity_Malnutrition_Apr_Jun2026_Report.pdf\">2 million</a> people are now in IPC Phase 4, more than double the number at the same time last year, indicating a sharp rise severity.</li>\n<li>Somalia remains one of the world’s most severe malnutrition crises, with <a rel=\"noreferrer noopener\" target=\"_blank\" href=\"https://fsnau.org/downloads/IPC_Somalia_Projection_Update_Acute_Food_Insecurity_Malnutrition_Apr_Jun2026_Report.pdf\">1.9 million</a> children acutely malnourished. Reduced services are increasing life-threatening risks for children. The latest IPC analysis indicates famine risk in Burhakaba (Southwest), where nearly 40 percent of children under five are acutely malnourished or worse.</li>\n<li>WFP remains the backbone of humanitarian response in Somalia, but funding gaps are significantly reducing reach. Humanitarian food assistance currently covers only 450,000 people, only 24 percent of the IPC Phase 4 (Emergency) population through August. This gap will have severe consequences for the most vulnerable populations. Urgent funding is needed to scale up assistance and prevent further deterioration.</li>\n</ul>\n              \n      \n      ",
      "contentSnippet": "Country: Somalia\nSource: World Food Programme\n\nPlease refer to the attached file.\nSomalia’s food security and nutrition situation is worsening beyond earlier projections, driven by consecutive failed rains, reduced humanitarian funding, and spillover effects from the Middle East crisis. Around 2 million people are now in IPC Phase 4, more than double the number at the same time last year, indicating a sharp rise severity.\nSomalia remains one of the world’s most severe malnutrition crises, with 1.9 million children acutely malnourished. Reduced services are increasing life-threatening risks for children. The latest IPC analysis indicates famine risk in Burhakaba (Southwest), where nearly 40 percent of children under five are acutely malnourished or worse.\nWFP remains the backbone of humanitarian response in Somalia, but funding gaps are significantly reducing reach. Humanitarian food assistance currently covers only 450,000 people, only 24 percent of the IPC Phase 4 (Emergency) population through August. This gap will have severe consequences for the most vulnerable populations. Urgent funding is needed to scale up assistance and prevent further deterioration.",
      "guid": "https://reliefweb.int/report/somalia/wfp-somalia-country-brief-june-2026",
      "categories": [
        "Somalia",
        "World Food Programme"
      ],
      "isoDate": "2026-06-28T07:56:56.000Z"
    },
    {
      "creator": "UN Resident Coordinator in Bangladesh",
      "title": "Bangladesh: Situation Report #5 - Measles Outbreak (25 June 2026)",
      "link": "https://reliefweb.int/report/bangladesh/bangladesh-situation-report-5-measles-outbreak-25-june-2026",
      "pubDate": "Sun, 28 Jun 2026 04:25:00 +0000",
      "author": "UN Resident Coordinator in Bangladesh",
      "enclosure": {
        "url": "https://reliefweb.int/attachments/943b133a-d62f-4820-8c54-4c7cbec030c1/SitRep_ICCG_MeaslesOutbreak_25%20June26.pdf",
        "length": "237172",
        "type": "application/pdf"
      },
      "content": "\n                            <div class=\"tag country\">Country: Bangladesh</div>\n                                      <div class=\"tag source\">Source: UN Resident Coordinator in Bangladesh</div>\n                                          <p><img src=\"https://reliefweb.int/sites/default/files/styles/thumbnail/public/previews/94/3b/943b133a-d62f-4820-8c54-4c7cbec030c1.png\" alt></p>\n                        <p>Please refer to the attached file.</p>\n                        <p>Bangladesh has reported more than 95,760 suspected and 11,390 confirmed measles cases and 596 suspected and 93 confirmed deaths across all 64 districts as of 25 June, with children under five accounting for 81 per cent of reported cases. Recent reporting suggests suspected cases are gradually declining, with the latest 7-day average at around 980 cases per day. However, transmission remains significant, with 996 suspected cases reported in the last 24 hours. More than 18.4 million children have been vaccinated through the nationwide measles rubella (MR) campaign, surpassing the initial target of 18 million children and reaching 102 per cent coverage. In the Rohingya refugee camps in Cox’s Bazar, the MR vaccination and Vitamin A supplementation campaign reached 94 per cent of the 178,024 targeted children. In Bhasan Char, the campaign achieved 99 per cent coverage.</p>\n              \n      \n      ",
      "contentSnippet": "Country: Bangladesh\nSource: UN Resident Coordinator in Bangladesh\n\nPlease refer to the attached file.\nBangladesh has reported more than 95,760 suspected and 11,390 confirmed measles cases and 596 suspected and 93 confirmed deaths across all 64 districts as of 25 June, with children under five accounting for 81 per cent of reported cases. Recent reporting suggests suspected cases are gradually declining, with the latest 7-day average at around 980 cases per day. However, transmission remains significant, with 996 suspected cases reported in the last 24 hours. More than 18.4 million children have been vaccinated through the nationwide measles rubella (MR) campaign, surpassing the initial target of 18 million children and reaching 102 per cent coverage. In the Rohingya refugee camps in Cox’s Bazar, the MR vaccination and Vitamin A supplementation campaign reached 94 per cent of the 178,024 targeted children. In Bhasan Char, the campaign achieved 99 per cent coverage.",
      "guid": "https://reliefweb.int/report/bangladesh/bangladesh-situation-report-5-measles-outbreak-25-june-2026",
      "categories": [
        "Bangladesh",
        "UN Resident Coordinator in Bangladesh"
      ],
      "isoDate": "2026-06-28T04:25:00.000Z"
    },
    {
      "creator": "UN Resident Coordinator in Bangladesh",
      "title": "Bangladesh: ICCG Meeting Notes (Date - 19 May 2026) [Meeting minutes]",
      "link": "https://reliefweb.int/report/bangladesh/bangladesh-iccg-meeting-notes-date-19-may-2026-meeting-minutes",
      "pubDate": "Sun, 28 Jun 2026 04:14:46 +0000",
      "author": "UN Resident Coordinator in Bangladesh",
      "enclosure": {
        "url": "https://reliefweb.int/attachments/f94c2d6e-02d1-431b-8b76-dad0a2f74c13/ICCG%20meeting%20notes%2019%20May%202026.pdf",
        "length": "273611",
        "type": "application/pdf"
      },
      "content": "\n                            <div class=\"tag country\">Country: Bangladesh</div>\n                                      <div class=\"tag source\">Source: UN Resident Coordinator in Bangladesh</div>\n                                          <p><img src=\"https://reliefweb.int/sites/default/files/styles/thumbnail/public/previews/f9/4c/f94c2d6e-02d1-431b-8b76-dad0a2f74c13.png\" alt></p>\n                        <p>Please refer to the attached file.</p>\n                      \n      \n      ",
      "contentSnippet": "Country: Bangladesh\nSource: UN Resident Coordinator in Bangladesh\n\nPlease refer to the attached file.",
      "guid": "https://reliefweb.int/report/bangladesh/bangladesh-iccg-meeting-notes-date-19-may-2026-meeting-minutes",
      "categories": [
        "Bangladesh",
        "UN Resident Coordinator in Bangladesh"
      ],
      "isoDate": "2026-06-28T04:14:46.000Z"
    },
    {
      "creator": "UN Resident Coordinator in Bangladesh",
      "title": "Bangladesh: ICCG Meeting Notes (Date - 16 June 2026) [Meeting minutes]",
      "link": "https://reliefweb.int/report/bangladesh/bangladesh-iccg-meeting-notes-date-16-june-2026-meeting-minutes",
      "pubDate": "Sun, 28 Jun 2026 04:10:01 +0000",
      "author": "UN Resident Coordinator in Bangladesh",
      "enclosure": {
        "url": "https://reliefweb.int/attachments/0befbd80-c292-4db8-b934-27825502e221/ICCG%20meeting%20notes%2016%20June%202026.pdf",
        "length": "265556",
        "type": "application/pdf"
      },
      "content": "\n                            <div class=\"tag country\">Country: Bangladesh</div>\n                                      <div class=\"tag source\">Source: UN Resident Coordinator in Bangladesh</div>\n                                          <p><img src=\"https://reliefweb.int/sites/default/files/styles/thumbnail/public/previews/0b/ef/0befbd80-c292-4db8-b934-27825502e221.png\" alt></p>\n                        <p>Please refer to the attached file.</p>\n                      \n      \n      ",
      "contentSnippet": "Country: Bangladesh\nSource: UN Resident Coordinator in Bangladesh\n\nPlease refer to the attached file.",
      "guid": "https://reliefweb.int/report/bangladesh/bangladesh-iccg-meeting-notes-date-16-june-2026-meeting-minutes",
      "categories": [
        "Bangladesh",
        "UN Resident Coordinator in Bangladesh"
      ],
      "isoDate": "2026-06-28T04:10:01.000Z"
    },
    {
      "creator": "UN Office for the Coordination of Humanitarian Affairs",
      "title": "Terremotos en Venezuela: Reporte de situación N.º 4 (27 de junio de 2026, Hora: 3:00 pm)",
      "link": "https://reliefweb.int/report/venezuela-bolivarian-republic/terremotos-en-venezuela-reporte-de-situacion-no-4-27-de-junio-de-2026-hora-300-pm",
      "pubDate": "Sun, 28 Jun 2026 00:33:52 +0000",
      "author": "UN Office for the Coordination of Humanitarian Affairs",
      "enclosure": {
        "url": "https://reliefweb.int/attachments/991bd356-74b9-4cfa-aceb-f312e9407563/VE_%20Situaci%C3%B3n%20por%20terremotos%20en%20Venezuela_OCHA_27%20Junio%202026_4.pdf",
        "length": "216416",
        "type": "application/pdf"
      },
      "content": "\n                            <div class=\"tag country\">Country: Venezuela (Bolivarian Republic of)</div>\n                                      <div class=\"tag source\">Source: UN Office for the Coordination of Humanitarian Affairs</div>\n                                                                                                <p><img src=\"https://reliefweb.int/sites/default/files/styles/thumbnail/public/previews/99/1b/991bd356-74b9-4cfa-aceb-f312e9407563.png\" alt></p>\n                        <p>Please refer to the attached file.</p>\n                        <p><strong>Reporte de situación N.º 4</strong><br><strong>Terremotos en Venezuela</strong><br><strong>27 de junio de 2026</strong><br><strong>Hora: 3:00 pm</strong></p>\n<p><strong>Destacados</strong></p>\n<ul><li>Dos sismos consecutivos de magnitud 7,2 y 7,5 se registraron el 24 de junio (18:00 hora local); <strong>las autoridades reportan más de 430 réplicas.</strong></li>\n<li>Al menos siete (7) estados impactado. La Guaira se mantiene como el estado con las mayores afectaciones.</li>\n<li>Balance oficial: <strong>1.430 personas fallecidas y 3.238 heridas;</strong> la cifra continúa en aumento.</li>\n<li>Se reportan <strong>más de 3.100 familias damnificadas.</strong></li>\n<li>Al menos <strong>1.423 infraestructuras se vieron afectadas</strong>.</li>\n<li>La respuesta se mantiene enfocada en las labores de búsqueda y rescate.</li>\n<li>Equipos de Búsqueda y Rescate Urbano (USAR) de 27 países continuán llegando al país y trabajan en las zonas más afectadas, en coordinación con OCHA.</li>\n<li><strong>El Coordinador Humanitario, Gianluca Rampolla, realizó este sábado una primera visita al estado La Guaira con agencias de Naciones Unidas para articular la respuesta con las autoridades.</strong></li>\n</ul><p><strong>Situación general</strong></p>\n<p>Venezuela enfrenta una emergencia nacional tras dos sismos consecutivos de gran magnitud (7,2 y 7,5) ocurridos el 24 de junio (18:00, hora local) en la región centro-norte, con epicentro sobre el eje San Felipe - Yumare - Montalbán (Yaracuy/Carabobo). Las autoridades reportan 430 réplicas. Tan solo la madrugada del sábado 26 de junio, se registraron 20, según reportes de medios locales, lo que mantiene condiciones de riesgo elevado.</p>\n<p>El balance oficial asciende a 1.430 personas fallecidas y 3.280 heridas. Autoridades también reportaron que tenían contabilizadas 3.142 familias damnificadas. Así mismo, hasta la tarde del viernes 26 de junio, se tenía registro de al menos 1.423 infraestructuras afectadas. Las cifras se mantienen en revisión a medida que avanzan las operaciones.</p>\n<p>La respuesta gubernamental durante las primeras horas se ha centrado en búsqueda y rescate, atención médica de emergencia y evaluación de daños. El impacto es severo, con mayor concentración en La Guaira, Distrito Capital, Miranda, Carabobo y Yaracuy. Naciones Unidas y sus organizaciones socias se encuentran en articulación para la siguiente fase de la respuesta.</p>\n              \n      \n      ",
      "contentSnippet": "Country: Venezuela (Bolivarian Republic of)\nSource: UN Office for the Coordination of Humanitarian Affairs\n\nPlease refer to the attached file.\nReporte de situación N.º 4\nTerremotos en Venezuela\n27 de junio de 2026\nHora: 3:00 pm\nDestacados\nDos sismos consecutivos de magnitud 7,2 y 7,5 se registraron el 24 de junio (18:00 hora local); las autoridades reportan más de 430 réplicas.\nAl menos siete (7) estados impactado. La Guaira se mantiene como el estado con las mayores afectaciones.\nBalance oficial: 1.430 personas fallecidas y 3.238 heridas; la cifra continúa en aumento.\nSe reportan más de 3.100 familias damnificadas.\nAl menos 1.423 infraestructuras se vieron afectadas.\nLa respuesta se mantiene enfocada en las labores de búsqueda y rescate.\nEquipos de Búsqueda y Rescate Urbano (USAR) de 27 países continuán llegando al país y trabajan en las zonas más afectadas, en coordinación con OCHA.\nEl Coordinador Humanitario, Gianluca Rampolla, realizó este sábado una primera visita al estado La Guaira con agencias de Naciones Unidas para articular la respuesta con las autoridades.\nSituación general\nVenezuela enfrenta una emergencia nacional tras dos sismos consecutivos de gran magnitud (7,2 y 7,5) ocurridos el 24 de junio (18:00, hora local) en la región centro-norte, con epicentro sobre el eje San Felipe - Yumare - Montalbán (Yaracuy/Carabobo). Las autoridades reportan 430 réplicas. Tan solo la madrugada del sábado 26 de junio, se registraron 20, según reportes de medios locales, lo que mantiene condiciones de riesgo elevado.\nEl balance oficial asciende a 1.430 personas fallecidas y 3.280 heridas. Autoridades también reportaron que tenían contabilizadas 3.142 familias damnificadas. Así mismo, hasta la tarde del viernes 26 de junio, se tenía registro de al menos 1.423 infraestructuras afectadas. Las cifras se mantienen en revisión a medida que avanzan las operaciones.\nLa respuesta gubernamental durante las primeras horas se ha centrado en búsqueda y rescate, atención médica de emergencia y evaluación de daños. El impacto es severo, con mayor concentración en La Guaira, Distrito Capital, Miranda, Carabobo y Yaracuy. Naciones Unidas y sus organizaciones socias se encuentran en articulación para la siguiente fase de la respuesta.",
      "guid": "https://reliefweb.int/report/venezuela-bolivarian-republic/terremotos-en-venezuela-reporte-de-situacion-no-4-27-de-junio-de-2026-hora-300-pm",
      "categories": [
        "Venezuela (Bolivarian Republic of)",
        "UN Office for the Coordination of Humanitarian Affairs",
        "Coordination",
        "Situation Report",
        "Earthquake"
      ],
      "isoDate": "2026-06-28T00:33:52.000Z"
    },
    {
      "creator": "UN Office for the Coordination of Humanitarian Affairs",
      "title": "Earthquakes in Venezuela: Situation Report No. 4 (27 June 2026, Time: 3:00 pm)",
      "link": "https://reliefweb.int/report/venezuela-bolivarian-republic/earthquakes-venezuela-situation-report-no-4-27-june-2026-time-300-pm",
      "pubDate": "Sun, 28 Jun 2026 00:10:18 +0000",
      "author": "UN Office for the Coordination of Humanitarian Affairs",
      "enclosure": {
        "url": "https://reliefweb.int/attachments/d78ef3a5-04b7-4259-8e42-1658555e994a/VE_%20Earthquake%20Situation%20in%20Venezuela_OCHA_27%20June%202026_4.pdf",
        "length": "213271",
        "type": "application/pdf"
      },
      "content": "\n                            <div class=\"tag country\">Country: Venezuela (Bolivarian Republic of)</div>\n                                      <div class=\"tag source\">Source: UN Office for the Coordination of Humanitarian Affairs</div>\n                                                                                                <p><img src=\"https://reliefweb.int/sites/default/files/styles/thumbnail/public/previews/d7/8e/d78ef3a5-04b7-4259-8e42-1658555e994a.png\" alt></p>\n                        <p>Please refer to the attached file.</p>\n                        <p><strong>Situation Report No. 4</strong><br><strong>Earthquakes in Venezuela</strong><br><strong>27 June 2026</strong><br><strong>Time: 3:00 pm</strong></p>\n<p><strong>Highlights</strong></p>\n<ul><li>Two consecutive earthquakes of magnitude 7.2 and 7.5 on 24 June (18:00 local time); authorities report more than <strong>430 aftershocks.</strong></li>\n<li>At least seven (7) states have been impacted. La Guaira continues to record the highest level of impact.</li>\n<li>Official toll: <strong>1,430 people dead and 3,238 injured</strong>; the figure continues to rise.</li>\n<li><strong>More than 3,100 families resulted displaced.</strong></li>\n<li><strong>At least 1,423 infrastructures were affected.</strong></li>\n<li>The response remains focused on search and rescue operations.</li>\n<li>Urban Search and Rescue (USAR) teams from 27 countries continue to arrive in the country and are operating in the most affected areas, in coordination with OCHA.</li>\n<li><strong>The Humanitarian Coordinator, Gianluca Rampolla, conducted an initial visit to La Guaira with United Nations agencies to coordinate the response with the authorities.</strong></li>\n</ul><p><strong>Situation overview</strong><br>\nVenezuela is facing a national emergency following the two consecutive high-magnitude earthquakes (7.2 and 7.5) of 24 June (18:00 local time) in the north-central region, with the epicentre off the coast some 28–30 km north-west of Montalbán (Carabobo). Authorities report more than 430 aftershocks, sustaining. In the early hours of Saturday, 26 June alone, 20 events were recorded, according to local media reports, maintaining a high-risk conditions.</p>\n<p>The official toll stands at 1,430 people dead and 3,280 injured. Authorities also reported that 3,142 families have been displaced. Additionally, as of the afternoon of Friday, 26 June, at least 1,423 infrastructures had been reported as affected. Figures remain under review as operations advance.</p>\n<p>The Government response in the initial hours has focused on search and rescue, emergency medical care and damage assessments. The impact is severe, with the highest concentration in the La Guaira, Capital District, Miranda, Carabobo and Yaracuy. The United Nations and its partner organizations are coordinating for the next phase of the response.</p>\n              \n      \n      ",
      "contentSnippet": "Country: Venezuela (Bolivarian Republic of)\nSource: UN Office for the Coordination of Humanitarian Affairs\n\nPlease refer to the attached file.\nSituation Report No. 4\nEarthquakes in Venezuela\n27 June 2026\nTime: 3:00 pm\nHighlights\nTwo consecutive earthquakes of magnitude 7.2 and 7.5 on 24 June (18:00 local time); authorities report more than 430 aftershocks.\nAt least seven (7) states have been impacted. La Guaira continues to record the highest level of impact.\nOfficial toll: 1,430 people dead and 3,238 injured; the figure continues to rise.\nMore than 3,100 families resulted displaced.\nAt least 1,423 infrastructures were affected.\nThe response remains focused on search and rescue operations.\nUrban Search and Rescue (USAR) teams from 27 countries continue to arrive in the country and are operating in the most affected areas, in coordination with OCHA.\nThe Humanitarian Coordinator, Gianluca Rampolla, conducted an initial visit to La Guaira with United Nations agencies to coordinate the response with the authorities.\nSituation overview\nThe official toll stands at 1,430 people dead and 3,280 injured. Authorities also reported that 3,142 families have been displaced. Additionally, as of the afternoon of Friday, 26 June, at least 1,423 infrastructures had been reported as affected. Figures remain under review as operations advance.\nThe Government response in the initial hours has focused on search and rescue, emergency medical care and damage assessments. The impact is severe, with the highest concentration in the La Guaira, Capital District, Miranda, Carabobo and Yaracuy. The United Nations and its partner organizations are coordinating for the next phase of the response.",
      "guid": "https://reliefweb.int/report/venezuela-bolivarian-republic/earthquakes-venezuela-situation-report-no-4-27-june-2026-time-300-pm",
      "categories": [
        "Venezuela (Bolivarian Republic of)",
        "UN Office for the Coordination of Humanitarian Affairs",
        "Coordination",
        "Situation Report",
        "Earthquake"
      ],
      "isoDate": "2026-06-28T00:10:18.000Z"
    },
    {
      "creator": "Health Cluster",
      "title": "Venezuela Health Cluster: Earthquakes Situation Report #2 (27 June 2026)",
      "link": "https://reliefweb.int/report/venezuela-bolivarian-republic/venezuela-health-cluster-earthquakes-situation-report-2-27-june-2026",
      "pubDate": "Sat, 27 Jun 2026 23:32:14 +0000",
      "author": "Health Cluster",
      "enclosure": {
        "url": "https://reliefweb.int/attachments/d6ed80b0-bba1-46d2-b1cf-e713c4e51c27/20260627_VEN_HC_SitrepV2final_ES.pdf",
        "length": "415727",
        "type": "application/pdf"
      },
      "content": "\n                            <div class=\"tag country\">Country: Venezuela (Bolivarian Republic of)</div>\n                                      <div class=\"tag source\">Sources: Health Cluster, Pan American Health Organization, World Health Organization</div>\n                                          <p><img src=\"https://reliefweb.int/sites/default/files/styles/thumbnail/public/previews/d6/ed/d6ed80b0-bba1-46d2-b1cf-e713c4e51c27.png\" alt></p>\n                        <p>Please refer to the attached files.</p>\n                        <p>El 26 de junio se consolidó un mecanismo único de respuesta ante la emergencia mediante la reunión del Clúster de Salud Ampliado junto al Ministerio de la Salud (MPPS), logrando integrar a actores estatales, agencias de Naciones Unidas y ONG para optimizar las operaciones en el terreno. Con el fin de priorizar y agilizar las labores de búsqueda y salvamento, las autoridades competentes establecieron restricciones temporales de acceso al estado La Guaira a partir de esa misma noche. Por su parte, la infraestructura sanitaria reporta compromisos estructurales en diversos centros asistenciales, lo que ha motivado la habilitación de áreas de atención externas y la activación de protocolos para localizar al personal de salud en las zonas de mayor impacto. Asimismo, se registra una interrupción generalizada de servicios básicos como agua, energía eléctrica y gas, obligando a la población a ubicarse preventivamente en espacios abiertos con el apoyo técnico de equipos internacionales de rescate. Finalmente, la evaluación de necesidades se canaliza a través de la Sala Situacional para orientar la asistencia técnica, ratificando al SEFAR (Las Adjuntas) como el nodo central para el acopio y redistribución de insumos, mientras se agilizan las importaciones y traslados terrestres de suministros médicos.</p>\n<p>-------------------</p>\n<p>On June 26, a unified emergency response mechanism was established through a meeting of the Expanded Health Cluster together with the Ministry of Health (MPPS), successfully bringing together government actors, United Nations agencies, and NGOs to optimize operations on the ground. In order to prioritize and expedite search and rescue efforts, the relevant authorities imposed temporary restrictions on access to the state of La Guaira beginning that same night. Meanwhile, health authorities report structural damage to various healthcare facilities, which has led to the establishment of outdoor treatment areas and the activation of protocols to locate healthcare personnel in the most affected areas. Furthermore, there has been a widespread disruption of basic services such as water, electricity, and gas, forcing the population to evacuate as a precautionary measure to open spaces with the technical support of international rescue teams. Finally, needs assessments are being coordinated through the Situation Room to guide technical assistance, confirming SEFAR (Las Adjuntas) as the central hub for the collection and redistribution of supplies, while imports and land transport of medical supplies are being expedited.</p>\n<p>Translated with DeepL.com (free version)</p>\n              \n      \n      ",
      "contentSnippet": "Country: Venezuela (Bolivarian Republic of)\nSources: Health Cluster, Pan American Health Organization, World Health Organization\n\nPlease refer to the attached files.\nEl 26 de junio se consolidó un mecanismo único de respuesta ante la emergencia mediante la reunión del Clúster de Salud Ampliado junto al Ministerio de la Salud (MPPS), logrando integrar a actores estatales, agencias de Naciones Unidas y ONG para optimizar las operaciones en el terreno. Con el fin de priorizar y agilizar las labores de búsqueda y salvamento, las autoridades competentes establecieron restricciones temporales de acceso al estado La Guaira a partir de esa misma noche. Por su parte, la infraestructura sanitaria reporta compromisos estructurales en diversos centros asistenciales, lo que ha motivado la habilitación de áreas de atención externas y la activación de protocolos para localizar al personal de salud en las zonas de mayor impacto. Asimismo, se registra una interrupción generalizada de servicios básicos como agua, energía eléctrica y gas, obligando a la población a ubicarse preventivamente en espacios abiertos con el apoyo técnico de equipos internacionales de rescate. Finalmente, la evaluación de necesidades se canaliza a través de la Sala Situacional para orientar la asistencia técnica, ratificando al SEFAR (Las Adjuntas) como el nodo central para el acopio y redistribución de insumos, mientras se agilizan las importaciones y traslados terrestres de suministros médicos.\n-------------------\nOn June 26, a unified emergency response mechanism was established through a meeting of the Expanded Health Cluster together with the Ministry of Health (MPPS), successfully bringing together government actors, United Nations agencies, and NGOs to optimize operations on the ground. In order to prioritize and expedite search and rescue efforts, the relevant authorities imposed temporary restrictions on access to the state of La Guaira beginning that same night. Meanwhile, health authorities report structural damage to various healthcare facilities, which has led to the establishment of outdoor treatment areas and the activation of protocols to locate healthcare personnel in the most affected areas. Furthermore, there has been a widespread disruption of basic services such as water, electricity, and gas, forcing the population to evacuate as a precautionary measure to open spaces with the technical support of international rescue teams. Finally, needs assessments are being coordinated through the Situation Room to guide technical assistance, confirming SEFAR (Las Adjuntas) as the central hub for the collection and redistribution of supplies, while imports and land transport of medical supplies are being expedited.\nTranslated with DeepL.com (free version)",
      "guid": "https://reliefweb.int/report/venezuela-bolivarian-republic/venezuela-health-cluster-earthquakes-situation-report-2-27-june-2026",
      "categories": [
        "Venezuela (Bolivarian Republic of)",
        "Health Cluster",
        "Pan American Health Organization",
        "World Health Organization"
      ],
      "isoDate": "2026-06-27T23:32:14.000Z"
    },
    {
      "creator": "UN Office for the Coordination of Humanitarian Affairs",
      "title": "Terremotos en Venezuela: Equipos de Búsqueda y Rescate Urbano (USAR) – Datos clave (al 27 de junio)",
      "link": "https://reliefweb.int/report/venezuela-bolivarian-republic/terremotos-en-venezuela-equipos-de-busqueda-y-rescate-urbano-usar-datos-clave-al-27-de-junio",
      "pubDate": "Sat, 27 Jun 2026 18:44:43 +0000",
      "author": "UN Office for the Coordination of Humanitarian Affairs",
      "enclosure": {
        "url": "https://reliefweb.int/attachments/f612f86f-374b-4f95-bcf1-8060d463bd74/20260627-Infographic-USARTeams-VENEZUELA-SP.pdf",
        "length": "359977",
        "type": "application/pdf"
      },
      "content": "\n                            <div class=\"tag country\">Country: Venezuela (Bolivarian Republic of)</div>\n                                      <div class=\"tag source\">Source: UN Office for the Coordination of Humanitarian Affairs</div>\n                                                                                                <p><img src=\"https://reliefweb.int/sites/default/files/styles/thumbnail/public/previews/f6/12/f612f86f-374b-4f95-bcf1-8060d463bd74.png\" alt></p>\n                        <p>Please refer to the attached Infographic.</p>\n                        <p>A solicitud del Gobierno de Venezuela, equipos USAR de 27 países, con más de 2.200 integrantes y 140 perros de búsqueda, han sido movilizados para localizar y rescatar a personas atrapadas bajo estructuras colapsadas y brindar atención médica inicial. La Oficina de Coordinación de Asuntos Humanitarios de las Naciones Unidas (OCHA) ha activado sus herramientas de respuesta a emergencias y está apoyando a los equipos a medida que llegan al país.</p>\n              \n      \n      ",
      "contentSnippet": "Country: Venezuela (Bolivarian Republic of)\nSource: UN Office for the Coordination of Humanitarian Affairs\n\nPlease refer to the attached Infographic.\nA solicitud del Gobierno de Venezuela, equipos USAR de 27 países, con más de 2.200 integrantes y 140 perros de búsqueda, han sido movilizados para localizar y rescatar a personas atrapadas bajo estructuras colapsadas y brindar atención médica inicial. La Oficina de Coordinación de Asuntos Humanitarios de las Naciones Unidas (OCHA) ha activado sus herramientas de respuesta a emergencias y está apoyando a los equipos a medida que llegan al país.",
      "guid": "https://reliefweb.int/report/venezuela-bolivarian-republic/terremotos-en-venezuela-equipos-de-busqueda-y-rescate-urbano-usar-datos-clave-al-27-de-junio",
      "categories": [
        "Venezuela (Bolivarian Republic of)",
        "UN Office for the Coordination of Humanitarian Affairs",
        "Coordination",
        "Infographic",
        "Earthquake"
      ],
      "isoDate": "2026-06-27T18:44:43.000Z"
    },
    {
      "creator": "Health Cluster",
      "title": "Clúster Salud Venezuela: Minuta Reunión del Clúster de Salud Ampliado Nacional - Junio 26 (2026)",
      "link": "https://reliefweb.int/report/venezuela-bolivarian-republic/cluster-salud-venezuela-minuta-reunion-del-cluster-de-salud-ampliado-nacional-junio-26-2026",
      "pubDate": "Sat, 27 Jun 2026 17:14:27 +0000",
      "author": "Health Cluster",
      "enclosure": {
        "url": "https://reliefweb.int/attachments/668fa164-92f6-4eca-bd3f-7aeb9171822a/Minuta%20de%20la%20Reuni%C3%B3n%20del%20Cl%C3%BAster%20ampliado%20de%20Salud%20-Caracas_.pdf",
        "length": "320613",
        "type": "application/pdf"
      },
      "content": "\n                            <div class=\"tag country\">Country: Venezuela (Bolivarian Republic of)</div>\n                                      <div class=\"tag source\">Sources: Health Cluster, Pan American Health Organization, World Health Organization</div>\n                                          <p><img src=\"https://reliefweb.int/sites/default/files/styles/thumbnail/public/previews/66/8f/668fa164-92f6-4eca-bd3f-7aeb9171822a.png\" alt></p>\n                        <p>Please refer to the attached file.</p>\n                        <p>Minuta de Reunión: Coordinación de Respuesta - Clúster de Salud<br>\nFecha: 26 de junio de 2026</p>\n              \n      \n      ",
      "contentSnippet": "Country: Venezuela (Bolivarian Republic of)\nSources: Health Cluster, Pan American Health Organization, World Health Organization\n\nPlease refer to the attached file.\nMinuta de Reunión: Coordinación de Respuesta - Clúster de Salud\nFecha: 26 de junio de 2026",
      "guid": "https://reliefweb.int/report/venezuela-bolivarian-republic/cluster-salud-venezuela-minuta-reunion-del-cluster-de-salud-ampliado-nacional-junio-26-2026",
      "categories": [
        "Venezuela (Bolivarian Republic of)",
        "Health Cluster",
        "Pan American Health Organization",
        "World Health Organization"
      ],
      "isoDate": "2026-06-27T17:14:27.000Z"
    },
    {
      "creator": "International Organization for Migration",
      "title": "Venezuela (República Bolivariana de): Respuesta a Terremotos — Reporte de Situación #1, 26 de junio de 2026",
      "link": "https://reliefweb.int/report/venezuela-bolivarian-republic/venezuela-republica-bolivariana-de-respuesta-terremotos-reporte-de-situacion-1-26-de-junio-de-2026",
      "pubDate": "Sat, 27 Jun 2026 16:41:48 +0000",
      "author": "International Organization for Migration",
      "enclosure": {
        "url": "https://reliefweb.int/attachments/71995606-51d5-4e37-a441-cb699e39346d/IOM%20SitRep%20No.%2001%20%E2%80%93%20Terremoto%20Venezuela%20-%2026%20June%202026%20.%20Espanol.pdf",
        "length": "1467052",
        "type": "application/pdf"
      },
      "content": "\n                            <div class=\"tag country\">Country: Venezuela (Bolivarian Republic of)</div>\n                                      <div class=\"tag source\">Source: International Organization for Migration</div>\n                                          <p><img src=\"https://reliefweb.int/sites/default/files/styles/thumbnail/public/previews/71/99/71995606-51d5-4e37-a441-cb699e39346d.png\" alt></p>\n                        <p>Please refer to the attached file.</p>\n                        <p>Este primer Reporte de Situación presenta un panorama general del impacto de los terremotos del 24 de junio en la República Bolivariana de Venezuela y describe la respuesta prevista de la OIM en apoyo a las poblaciones afectadas y a los esfuerzos nacionales.</p>\n<p><strong>Aspectos destacados</strong></p>\n<p>Dos terremotos de gran magnitud, de Mw 7.2 y Mw 7.5, afectaron el centro-norte de Venezuela el 24 de junio, causando daños generalizados en La Guaira, Caracas, Miranda, Carabobo y Yaracuy.</p>\n<p>La Guaira ha sido identificada como la zona más afectada, con niveles significativos de destrucción reportados.</p>\n<p>Se han registrado interrupciones en infraestructura crítica, incluyendo electricidad, suministro de agua, telecomunicaciones, sistemas de transporte, el Metro de Caracas y el Aeropuerto Internacional de Maiquetía.</p>\n<p>El Gobierno ha declarado el estado de emergencia y activado los mecanismos nacionales de respuesta.</p>\n<p><strong>Cifras clave</strong></p>\n<p>Al menos 920 personas fallecidas.</p>\n<p>Aproximadamente 3,360 personas heridas.</p>\n<p>Más de 214 réplicas registradas hasta la mañana del 25 de junio.</p>\n<p>Se espera que las cifras de víctimas aumenten a medida que continúan las operaciones de búsqueda y rescate.</p>\n<p><strong>Prioridades de respuesta de la OIM</strong></p>\n<p>La OIM está movilizando capacidades internas para apoyar la respuesta al terremoto, con intervenciones previstas en albergue de emergencia y artículos de primera necesidad, salud y salud mental y apoyo psicosocial, agua, saneamiento e higiene, CCCM/gestión de sitios, protección, y datos y evaluaciones de necesidades.</p>\n<p>Las actividades prioritarias incluyen la provisión de materiales de albergue de emergencia y artículos esenciales para el hogar, el despliegue de equipos móviles de salud, el apoyo a establecimientos de salud, evaluaciones rápidas, monitoreo de sitios, análisis de riesgos de protección, rutas de derivación y productos de información basados en DTM para orientar la coordinación y la focalización de la respuesta.</p>\n              \n      \n      ",
      "contentSnippet": "Country: Venezuela (Bolivarian Republic of)\nSource: International Organization for Migration\n\nPlease refer to the attached file.\nEste primer Reporte de Situación presenta un panorama general del impacto de los terremotos del 24 de junio en la República Bolivariana de Venezuela y describe la respuesta prevista de la OIM en apoyo a las poblaciones afectadas y a los esfuerzos nacionales.\nAspectos destacados\nDos terremotos de gran magnitud, de Mw 7.2 y Mw 7.5, afectaron el centro-norte de Venezuela el 24 de junio, causando daños generalizados en La Guaira, Caracas, Miranda, Carabobo y Yaracuy.\nLa Guaira ha sido identificada como la zona más afectada, con niveles significativos de destrucción reportados.\nSe han registrado interrupciones en infraestructura crítica, incluyendo electricidad, suministro de agua, telecomunicaciones, sistemas de transporte, el Metro de Caracas y el Aeropuerto Internacional de Maiquetía.\nEl Gobierno ha declarado el estado de emergencia y activado los mecanismos nacionales de respuesta.\nCifras clave\nAl menos 920 personas fallecidas.\nAproximadamente 3,360 personas heridas.\nMás de 214 réplicas registradas hasta la mañana del 25 de junio.\nSe espera que las cifras de víctimas aumenten a medida que continúan las operaciones de búsqueda y rescate.\nPrioridades de respuesta de la OIM\nLa OIM está movilizando capacidades internas para apoyar la respuesta al terremoto, con intervenciones previstas en albergue de emergencia y artículos de primera necesidad, salud y salud mental y apoyo psicosocial, agua, saneamiento e higiene, CCCM/gestión de sitios, protección, y datos y evaluaciones de necesidades.\nLas actividades prioritarias incluyen la provisión de materiales de albergue de emergencia y artículos esenciales para el hogar, el despliegue de equipos móviles de salud, el apoyo a establecimientos de salud, evaluaciones rápidas, monitoreo de sitios, análisis de riesgos de protección, rutas de derivación y productos de información basados en DTM para orientar la coordinación y la focalización de la respuesta.",
      "guid": "https://reliefweb.int/report/venezuela-bolivarian-republic/venezuela-republica-bolivariana-de-respuesta-terremotos-reporte-de-situacion-1-26-de-junio-de-2026",
      "categories": [
        "Venezuela (Bolivarian Republic of)",
        "International Organization for Migration"
      ],
      "isoDate": "2026-06-27T16:41:48.000Z"
    },
    {
      "creator": "UN Office for the Coordination of Humanitarian Affairs",
      "title": "Lebanon: Flash Update #38 - Escalation of hostilities in Lebanon (as of 25 June 2026)",
      "link": "https://reliefweb.int/report/lebanon/lebanon-flash-update-38-escalation-hostilities-lebanon-25-june-2026",
      "pubDate": "Sat, 27 Jun 2026 16:10:39 +0000",
      "author": "UN Office for the Coordination of Humanitarian Affairs",
      "enclosure": {
        "url": "https://reliefweb.int/attachments/ff749981-1d10-4192-94c3-15e5ac3f704c/OCHA_Lebanon_Flash_Update%20No%2038.pdf",
        "length": "311263",
        "type": "application/pdf"
      },
      "content": "\n                            <div class=\"tag country\">Country: Lebanon</div>\n                                      <div class=\"tag source\">Source: UN Office for the Coordination of Humanitarian Affairs</div>\n                                          <p><img src=\"https://reliefweb.int/sites/default/files/styles/thumbnail/public/previews/ff/74/ff749981-1d10-4192-94c3-15e5ac3f704c.png\" alt></p>\n                        <p>Please refer to the attached file.</p>\n                        <p><strong>HIGHLIGHTS</strong></p>\n<ul><li>Displacement fell to <strong>59,700 people in shelters (down from over 140,000)</strong>, while more than <strong>523,000 people have begun returning</strong>, although movements remain cautious and often temporary.</li>\n<li>Ongoing insecurity, <strong>UXO contamination</strong>, and widespread destruction continue to pose serious risks, particularly in areas near the <strong>IDF-declared military zone</strong>.</li>\n<li>Damaged roads and limited infrastructure—especially in southern Lebanon—continue to <strong>restrict access</strong>, while gaps in <strong>water, electricity, and telecommunications</strong> hinder service delivery and coordination.</li>\n<li>Humanitarian needs remain <strong>significant across displacement and return areas</strong>, with priority needs including food, medicines, and fuel, while <strong>funding gaps continue to constrain the response</strong>.</li>\n</ul>\n              \n      \n      ",
      "contentSnippet": "Country: Lebanon\nSource: UN Office for the Coordination of Humanitarian Affairs\n\nPlease refer to the attached file.\nHIGHLIGHTS\nDisplacement fell to 59,700 people in shelters (down from over 140,000), while more than 523,000 people have begun returning, although movements remain cautious and often temporary.\nOngoing insecurity, UXO contamination, and widespread destruction continue to pose serious risks, particularly in areas near the IDF-declared military zone.\nDamaged roads and limited infrastructure—especially in southern Lebanon—continue to restrict access, while gaps in water, electricity, and telecommunications hinder service delivery and coordination.\nHumanitarian needs remain significant across displacement and return areas, with priority needs including food, medicines, and fuel, while funding gaps continue to constrain the response.",
      "guid": "https://reliefweb.int/report/lebanon/lebanon-flash-update-38-escalation-hostilities-lebanon-25-june-2026",
      "categories": [
        "Lebanon",
        "UN Office for the Coordination of Humanitarian Affairs"
      ],
      "isoDate": "2026-06-27T16:10:39.000Z"
    },
    {
      "creator": "UN Office for the Coordination of Humanitarian Affairs",
      "title": "Venezuela Earthquakes: Urban Search and Rescue (USAR) Team Snapshot (As of 27 June)",
      "link": "https://reliefweb.int/report/venezuela-bolivarian-republic/venezuela-earthquakes-urban-search-and-rescue-usar-team-snapshot-27-june",
      "pubDate": "Sat, 27 Jun 2026 15:08:51 +0000",
      "author": "UN Office for the Coordination of Humanitarian Affairs",
      "enclosure": {
        "url": "https://reliefweb.int/attachments/a3e30d5f-0f96-4da1-b8f8-9b8ccfb2e13e/20260627-Infographic-USARTeams-VENEZUELA.pdf",
        "length": "329474",
        "type": "application/pdf"
      },
      "content": "\n                            <div class=\"tag country\">Country: Venezuela (Bolivarian Republic of)</div>\n                                      <div class=\"tag source\">Source: UN Office for the Coordination of Humanitarian Affairs</div>\n                                                                                                <p><img src=\"https://reliefweb.int/sites/default/files/styles/thumbnail/public/previews/a3/e3/a3e30d5f-0f96-4da1-b8f8-9b8ccfb2e13e.png\" alt></p>\n                        <p>Please refer to the attached Infographic.</p>\n                        <p>At the request of the Government of Venezuela, USAR teams from 27 countries, with more than 2,200 personnel and 140 search dogs, have been mobilized to locate and extract people trapped by collapsed structures and provide initial medical support. The United Nations Office for the Coordination of Humanitarian Affairs (OCHA) has activated its emergency response tools and is supporting the teams as they arrive in the country.</p>\n              \n      \n      ",
      "contentSnippet": "Country: Venezuela (Bolivarian Republic of)\nSource: UN Office for the Coordination of Humanitarian Affairs\n\nPlease refer to the attached Infographic.\nAt the request of the Government of Venezuela, USAR teams from 27 countries, with more than 2,200 personnel and 140 search dogs, have been mobilized to locate and extract people trapped by collapsed structures and provide initial medical support. The United Nations Office for the Coordination of Humanitarian Affairs (OCHA) has activated its emergency response tools and is supporting the teams as they arrive in the country.",
      "guid": "https://reliefweb.int/report/venezuela-bolivarian-republic/venezuela-earthquakes-urban-search-and-rescue-usar-team-snapshot-27-june",
      "categories": [
        "Venezuela (Bolivarian Republic of)",
        "UN Office for the Coordination of Humanitarian Affairs",
        "Coordination",
        "Infographic",
        "Earthquake"
      ],
      "isoDate": "2026-06-27T15:08:51.000Z"
    },
    {
      "creator": "International Organization for Migration",
      "title": "Venezuela (Bolivarian Republic of): Earthquake Response Situation Report #1, 26 June 2026",
      "link": "https://reliefweb.int/report/venezuela-bolivarian-republic/venezuela-bolivarian-republic-earthquake-response-situation-report-1-26-june-2026",
      "pubDate": "Sat, 27 Jun 2026 02:45:45 +0000",
      "author": "International Organization for Migration",
      "enclosure": {
        "url": "https://reliefweb.int/attachments/673f3da4-273d-4940-9e2c-2ae646abeee7/IOM%20SitRep%20No.%2001%20%E2%80%93%20Earthquake%20Venezuela%20-%2026%20June%202026.pdf",
        "length": "1462165",
        "type": "application/pdf"
      },
      "content": "\n                            <div class=\"tag country\">Country: Venezuela (Bolivarian Republic of)</div>\n                                      <div class=\"tag source\">Source: International Organization for Migration</div>\n                                          <p><img src=\"https://reliefweb.int/sites/default/files/styles/thumbnail/public/previews/67/3f/673f3da4-273d-4940-9e2c-2ae646abeee7.png\" alt></p>\n                        <p>Please refer to the attached file.</p>\n                        <p>This first Situation Report provides an overview of the impact of the 24 June earthquakes in the Bolivarian Republic of Venezuela and outlines IOM’s planned response in support of affected populations and national efforts.</p>\n<p><strong>Highlights</strong></p>\n<ul><li>Two major earthquakes of Mw 7.2 and Mw 7.5 struck central-northern Venezuela on 24 June, causing widespread damage across La Guaira, Caracas, Miranda, Carabobo and Yaracuy.</li>\n<li>La Guaira has been identified as the most severely affected area, with significant destruction reported.</li>\n<li>Critical infrastructure has been disrupted, including electricity, water supply, telecommunications, transport systems, the Caracas Metro and Maiquetía International Airport.</li>\n<li>The Government has declared a state of emergency and activated national response mechanisms.</li>\n</ul><p><strong>Key figures</strong></p>\n<ul><li>At least 920 people reported dead.</li>\n<li>Approximately 3,360 people injured.</li>\n<li>More than 214 aftershocks recorded as of the morning of 25 June.</li>\n<li>Casualty figures are expected to rise as search-and-rescue operations continue.</li>\n</ul><p><strong>IOM response priorities</strong></p>\n<p>IOM is mobilizing internal capacities to support the earthquake response, with planned interventions focused on emergency shelter and core relief items, health and mental health and psychosocial support, WASH, CCCM/site management, protection, and data and needs assessments.</p>\n<p>Priority activities include the provision of emergency shelter materials and essential household items, deployment of mobile health teams, support to health facilities, rapid assessments, site monitoring, protection risk analysis, referral pathways and DTM-based data products to inform coordination and targeting.</p>\n              \n      \n      ",
      "contentSnippet": "Country: Venezuela (Bolivarian Republic of)\nSource: International Organization for Migration\n\nPlease refer to the attached file.\nThis first Situation Report provides an overview of the impact of the 24 June earthquakes in the Bolivarian Republic of Venezuela and outlines IOM’s planned response in support of affected populations and national efforts.\nHighlights\nTwo major earthquakes of Mw 7.2 and Mw 7.5 struck central-northern Venezuela on 24 June, causing widespread damage across La Guaira, Caracas, Miranda, Carabobo and Yaracuy.\nLa Guaira has been identified as the most severely affected area, with significant destruction reported.\nCritical infrastructure has been disrupted, including electricity, water supply, telecommunications, transport systems, the Caracas Metro and Maiquetía International Airport.\nThe Government has declared a state of emergency and activated national response mechanisms.\nKey figures\nAt least 920 people reported dead.\nApproximately 3,360 people injured.\nMore than 214 aftershocks recorded as of the morning of 25 June.\nCasualty figures are expected to rise as search-and-rescue operations continue.\nIOM response priorities\nIOM is mobilizing internal capacities to support the earthquake response, with planned interventions focused on emergency shelter and core relief items, health and mental health and psychosocial support, WASH, CCCM/site management, protection, and data and needs assessments.\nPriority activities include the provision of emergency shelter materials and essential household items, deployment of mobile health teams, support to health facilities, rapid assessments, site monitoring, protection risk analysis, referral pathways and DTM-based data products to inform coordination and targeting.",
      "guid": "https://reliefweb.int/report/venezuela-bolivarian-republic/venezuela-bolivarian-republic-earthquake-response-situation-report-1-26-june-2026",
      "categories": [
        "Venezuela (Bolivarian Republic of)",
        "International Organization for Migration"
      ],
      "isoDate": "2026-06-27T02:45:45.000Z"
    }
  ]
}